pptx_o_matic/__init__.py
pptx_o_matic/img2pptx.py
pptx_o_matic/pdf2pptx.py
pptx_o_matic-0.2.0.dist-info/LICENSE
pptx_o_matic-0.2.0.dist-info/METADATA
pptx_o_matic-0.2.0.dist-info/WHEEL
pptx_o_matic-0.2.0.dist-info/entry_points.txt
pptx_o_matic-0.2.0.dist-info/top_level.txt
pptx_o_matic-0.2.0.dist-info/RECORD
